trace_view-0.1.0.data/scripts/tv
trace_view-0.1.0.dist-info/METADATA
trace_view-0.1.0.dist-info/WHEEL
traceview/__init__.py
traceview/_binary.py
traceview/otel.py
traceview/py.typed
traceview/server.py
trace_view-0.1.0.dist-info/RECORD
