Metadata-Version: 2.4
Name: trace-view
Version: 0.1.0
Requires-Dist: trace-view[otel] ; extra == 'full'
Requires-Dist: opentelemetry-instrumentation-requests>=0.40b0 ; extra == 'full'
Requires-Dist: opentelemetry-instrumentation-httpx>=0.40b0 ; extra == 'full'
Requires-Dist: opentelemetry-api>=1.20.0 ; extra == 'otel'
Requires-Dist: opentelemetry-sdk>=1.20.0 ; extra == 'otel'
Requires-Dist: opentelemetry-exporter-otlp-proto-http>=1.20.0 ; extra == 'otel'
Provides-Extra: full
Provides-Extra: otel
Summary: Local OpenTelemetry trace viewer for GenAI applications
Keywords: opentelemetry,tracing,observability,genai,llm
License: MIT
Requires-Python: >=3.9
Project-URL: Homepage, https://github.com/rmarmarma/traceview
Project-URL: Repository, https://github.com/rmarmarma/traceview
